.gitignore
MANIFEST.in
README.txt
buildout.cfg
setup.py
aws/__init__.py
aws.pdfbook.egg-info/PKG-INFO
aws.pdfbook.egg-info/SOURCES.txt
aws.pdfbook.egg-info/dependency_links.txt
aws.pdfbook.egg-info/entry_points.txt
aws.pdfbook.egg-info/namespace_packages.txt
aws.pdfbook.egg-info/not-zip-safe
aws.pdfbook.egg-info/requires.txt
aws.pdfbook.egg-info/top_level.txt
aws/pdfbook/__init__.py
aws/pdfbook/config.py
aws/pdfbook/configure.zcml
aws/pdfbook/conversions.py
aws/pdfbook/interfaces.py
aws/pdfbook/pdf_icon.gif
aws/pdfbook/refresh.txt
aws/pdfbook/upgrades.py
aws/pdfbook/utils.py
aws/pdfbook/browser/__init__.py
aws/pdfbook/browser/configure.zcml
aws/pdfbook/browser/contentform.py
aws/pdfbook/browser/controlpanel.py
aws/pdfbook/browser/transformers.py
aws/pdfbook/browser/transformers.zcml
aws/pdfbook/browser/templates/atdocument.pt
aws/pdfbook/browser/templates/atevent.pt
aws/pdfbook/browser/templates/atfolder.pt
aws/pdfbook/browser/templates/atlink.pt
aws/pdfbook/browser/templates/atnewsitem.pt
aws/pdfbook/browser/templates/attopic.pt
aws/pdfbook/browser/templates/contentoptions.pt
aws/pdfbook/browser/templates/defaultlayout.pt
aws/pdfbook/browser/templates/masterpage.pt
aws/pdfbook/browser/templates/pdfbookprint.pt
aws/pdfbook/locales/README.txt
aws/pdfbook/locales/aws.pdfbook.pot
aws/pdfbook/locales/updatelocales.py
aws/pdfbook/locales/fr/LC_MESSAGES/aws.pdfbook.mo
aws/pdfbook/locales/fr/LC_MESSAGES/aws.pdfbook.po
aws/pdfbook/locales/pt_BR/LC_MESSAGES/aws.pdfbook.mo
aws/pdfbook/locales/pt_BR/LC_MESSAGES/aws.pdfbook.po
aws/pdfbook/profiles/default/actionicons.xml
aws/pdfbook/profiles/default/actions.xml
aws/pdfbook/profiles/default/aws.pdfbook.txt
aws/pdfbook/profiles/default/browserlayer.xml
aws/pdfbook/profiles/default/controlpanel.xml
aws/pdfbook/profiles/default/metadata.xml
aws/pdfbook/profiles/default/propertiestool.xml
aws/pdfbook/tests/__init__.py
aws/pdfbook/tests/common.py
aws/pdfbook/tests/test_docaction.txt
aws/pdfbook/tests/test_doctests.py
aws/pdfbook/tests/test_setup.py
docs/HISTORY.txt
docs/LICENSE.txt