Metadata-Version: 1.1
Name: aws.pdfbook
Version: 1.1
Summary: Download Plone content views as PDF
Home-page: http://pypi.python.org/pypi/aws.pdfbook
Author: Alter Way Solutions
Author-email: support@ingeniweb.com
License: GPL
Keywords: pdf plone
Platform: UNKNOWN
Classifier: Programming Language :: Python
Classifier: Framework :: Plone
Classifier: Development Status :: 4 - Beta
Classifier: License :: OSI Approved :: GNU General Public License (GPL)
Classifier: Operating System :: OS Independent
